docx_utils/__init__.py
docx_utils/__main__.py
docx_utils/cli.py
docx_utils/exceptions.py
docx_utils/flatten.py
docx_utils-0.1.3.dist-info/AUTHORS.rst
docx_utils-0.1.3.dist-info/LICENSE.rst
docx_utils-0.1.3.dist-info/METADATA
docx_utils-0.1.3.dist-info/WHEEL
docx_utils-0.1.3.dist-info/entry_points.txt
docx_utils-0.1.3.dist-info/top_level.txt
docx_utils-0.1.3.dist-info/RECORD
