Metadata-Version: 2.1
Name: docx-utils
Version: 0.1.3
Summary: Creation and manipulation of Open XML documents (mainly docx).
Home-page: https://github.com/tantale/docx_utils
Author: Laurent LAPORTE
Author-email: tantale.solutions@gmail.com
License: MIT License
Keywords: Microsoft,Office,Word,Excel,PowerPoint,docx,xlsx,pptx,XML
Platform: posix
Platform: nt
Classifier: Development Status :: 5 - Production/Stable
Classifier: Intended Audience :: Developers
Classifier: License :: OSI Approved :: MIT License
Classifier: Operating System :: Unix
Classifier: Operating System :: POSIX
Classifier: Operating System :: Microsoft :: Windows
Classifier: Programming Language :: Python
Classifier: Programming Language :: Python :: 2.7
Classifier: Programming Language :: Python :: 3
Classifier: Programming Language :: Python :: 3.4
Classifier: Programming Language :: Python :: 3.5
Classifier: Programming Language :: Python :: 3.6
Classifier: Programming Language :: Python :: 3.7
Classifier: Programming Language :: Python :: 3.8
Classifier: Programming Language :: Python :: 3.9
Classifier: Programming Language :: Python :: Implementation :: CPython
Classifier: Topic :: Utilities
Requires-Python: >= 2.7, != 3.0.*, != 3.1.*, != 3.2.*, != 3.3.*, != 3.4.*, < 4
Requires-Dist: click
Requires-Dist: six
Requires-Dist: lxml
Requires-Dist: enum34 ; python_version < "3.4"
Provides-Extra: dev
Requires-Dist: tox (<4) ; extra == 'dev'
Requires-Dist: zipp (<2) ; (python_version < "3") and extra == 'dev'
Requires-Dist: configparser (<5) ; (python_version < "3") and extra == 'dev'
Requires-Dist: virtualenv (<20) ; (python_version < "3" and sys_platform == "win32") and extra == 'dev'
Provides-Extra: test
Requires-Dist: pytest (==4.6.11) ; extra == 'test'
Requires-Dist: pytest-cov (==2.5.1) ; extra == 'test'
Requires-Dist: mock (==3.0.5) ; extra == 'test'
Requires-Dist: coverage (==5.0.4) ; extra == 'test'
Requires-Dist: zipp (==1.2.0) ; (python_version < "3") and extra == 'test'
Requires-Dist: configparser (==4.0.2) ; (python_version < "3") and extra == 'test'
Requires-Dist: coverage (==5.0.4) ; (python_version < "3") and extra == 'test'
